kivy_garden/painter/__init__.py
kivy_garden/painter/_version.py
kivy_garden/painter/tests/test_import.py
kivy_garden.painter-0.2.4.dist-info/AUTHORS.txt
kivy_garden.painter-0.2.4.dist-info/LICENSE.txt
kivy_garden.painter-0.2.4.dist-info/METADATA
kivy_garden.painter-0.2.4.dist-info/WHEEL
kivy_garden.painter-0.2.4.dist-info/top_level.txt
kivy_garden.painter-0.2.4.dist-info/RECORD
